nonebot_plugin_nya_music/__init__.py
nonebot_plugin_nya_music/config.py
nonebot_plugin_nya_music/data_handle.py
nonebot_plugin_nya_music/font/HYWenHei-85W.ttf
nonebot_plugin_nya_music-0.1.4.dist-info/METADATA
nonebot_plugin_nya_music-0.1.4.dist-info/WHEEL
nonebot_plugin_nya_music-0.1.4.dist-info/RECORD
