Metadata-Version: 2.1
Name: nonebot-plugin-nya-music
Version: 0.1.4
Summary: Nonebot2 喵喵点歌，可听歌可下载
Home-page: https://github.com/nikissXI/nonebot_plugins/tree/main/nonebot_plugin_nya_music
License: MIT
Author: nikissXI
Author-email: 1299577815@qq.com
Requires-Python: >=3.8
Classifier: License :: OSI Approved :: MIT License
Classifier: Programming Language :: Python :: 3
Classifier: Programming Language :: Python :: 3.8
Classifier: Programming Language :: Python :: 3.9
Classifier: Programming Language :: Python :: 3.10
Classifier: Programming Language :: Python :: 3.11
Requires-Dist: Pillow (>=9.0.0)
Requires-Dist: httpx (>=0.22.0)
Requires-Dist: nonebot-adapter-onebot (>=2.0.0)
Requires-Dist: nonebot2 (>=2.0.0rc1)
Project-URL: Documentation, https://github.com/nikissXI/nonebot_plugins/tree/main/nonebot_plugin_nya_music#README.md
Project-URL: Repository, https://github.com/nikissXI/nonebot_plugins/tree/main/nonebot_plugin_nya_music
